KratosMultiphysics/MappingApplication/__init__.py
KratosMultiphysics/MappingApplication/empire_mortar_mapper.py
KratosMultiphysics/MappingApplication/python_mapper.py
KratosMultiphysics/MappingApplication/python_mapper_factory.py
KratosMultiphysics/MappingApplication/serial_output_process.py
KratosMultiphysics/.libs/KratosMappingApplication.pyd
KratosMultiphysics/.libs/KratosMappingCore.dll
KratosMultiphysics/.libs/KratosMappingCore.lib
kratosmappingapplication-10.4.0.dist-info/METADATA
kratosmappingapplication-10.4.0.dist-info/WHEEL
kratosmappingapplication-10.4.0.dist-info/RECORD
